textextraction/__init__.py
textextraction/_markdown_output.py
textextraction/_table_utils.py
textextraction/cli.py
textextraction/image_processor.py
textextraction/pdf_processor.py
textextraction/pdf_unlocker.py
textextraction/scanned_pdf_processor.py
textextraction-0.1.4.dist-info/licenses/LICENSE
textextraction-0.1.4.dist-info/METADATA
textextraction-0.1.4.dist-info/WHEEL
textextraction-0.1.4.dist-info/top_level.txt
textextraction-0.1.4.dist-info/RECORD
