Metadata-Version: 2.4
Name: textextraction
Version: 0.1.4
Summary: Extract and process text from images and PDFs
Author-email: Nikhil K Singh <nsr.nikhilsingh@gmail.com>
License-Expression: MIT
Project-URL: Documentation, https://textextraction.readthedocs.io/
Project-URL: Bug Reports, https://github.com/Nikhil-K-Singh/textextraction/issues
Project-URL: Source Code, https://github.com/Nikhil-K-Singh/textextraction
Keywords: ocr,text extraction,pdf,image processing,document processing,table detection
Classifier: Development Status :: 4 - Beta
Classifier: Intended Audience :: Developers
Classifier: Intended Audience :: Science/Research
Classifier: Programming Language :: Python :: 3
Classifier: Programming Language :: Python :: 3.8
Classifier: Programming Language :: Python :: 3.9
Classifier: Programming Language :: Python :: 3.10
Classifier: Programming Language :: Python :: 3.11
Classifier: Operating System :: OS Independent
Classifier: Topic :: Scientific/Engineering :: Image Recognition
Classifier: Topic :: Text Processing :: General
Requires-Python: >=3.8
License-File: LICENSE
Requires-Dist: nltk==3.9.1
Requires-Dist: Pillow==11.2.1
Requires-Dist: pdfminer.six==20250327
Requires-Dist: pytesseract==0.3.13
Requires-Dist: pdf2image==1.17.0
Requires-Dist: regex==2024.11.6
Requires-Dist: easyocr==1.7.2
Requires-Dist: pdfplumber==0.11.6
Requires-Dist: opencv-python==4.11.0.86
Requires-Dist: numpy==2.0.2
Requires-Dist: camelot-py==1.0.0
Requires-Dist: tabulate==0.9.0
Requires-Dist: pymupdf==1.25.0
Provides-Extra: dev
Requires-Dist: pytest>=7.0.0; extra == "dev"
Requires-Dist: pytest-cov>=4.0.0; extra == "dev"
Requires-Dist: flake8>=6.0.0; extra == "dev"
Requires-Dist: black>=23.0.0; extra == "dev"
Requires-Dist: isort>=5.0.0; extra == "dev"
Requires-Dist: mypy>=1.0.0; extra == "dev"
Requires-Dist: sphinx>=7.0.0; extra == "dev"
Provides-Extra: docs
Requires-Dist: sphinx>=7.0.0; extra == "docs"
Requires-Dist: sphinx-rtd-theme>=1.3.0; extra == "docs"
Requires-Dist: sphinx-autodoc-typehints>=1.25.2; extra == "docs"
Requires-Dist: sphinxcontrib-napoleon>=0.7; extra == "docs"
Requires-Dist: docutils>=0.20; extra == "docs"
Dynamic: license-file
